<?xml version="1.0" encoding="UTF-8" ?>
<NotepadPlus>
    <Session activeView="0">
        <mainView activeIndex="0">
            <File firstVisibleLine="0" xOffset="0" scrollWidth="3347" startPos="544" endPos="544" selMode="0" offset="0" wrapCount="1" lang="Batch" encoding="-1" userReadOnly="no" filename="C:\Users\doria\Downloads\GitHub\dorian.gravier.github.io\files\configBU\RUN_ConfigBU.bat" backupFilePath="C:\Users\doria\scoop\apps\notepadplusplus\8.7.5\backup\RUN_ConfigBU.bat@2025-02-01_174230" originalFileLastModifTimestamp="1027743173" originalFileLastModifTimestampHigh="31159496" tabColourId="-1" RTL="no" tabPinned="no" mapFirstVisibleDisplayLine="-1" mapFirstVisibleDocLine="-1" mapLastVisibleDocLine="-1" mapNbLine="-1" mapHigherPos="-1" mapWidth="-1" mapHeight="-1" mapKByteInDoc="512" mapWrapIndentMode="-1" mapIsWrap="no" />
            <File firstVisibleLine="0" xOffset="0" scrollWidth="220901" startPos="799" endPos="799" selMode="0" offset="0" wrapCount="1" lang="Md Drakula" encoding="-1" userReadOnly="no" filename="C:\Users\doria\Downloads\gdrive\RR\2025\20250419__GP_Osterhas\ToDo_GP-Osterhas.md" backupFilePath="" originalFileLastModifTimestamp="-837364288" originalFileLastModifTimestampHigh="31149402" tabColourId="-1" RTL="no" tabPinned="no" mapFirstVisibleDisplayLine="-1" mapFirstVisibleDocLine="-1" mapLastVisibleDocLine="-1" mapNbLine="-1" mapHigherPos="-1" mapWidth="-1" mapHeight="-1" mapKByteInDoc="512" mapWrapIndentMode="-1" mapIsWrap="no" />
            <File firstVisibleLine="0" xOffset="0" scrollWidth="1879" startPos="670" endPos="670" selMode="0" offset="0" wrapCount="1" lang="Md Drakula" encoding="-1" userReadOnly="no" filename="C:\Users\doria\Downloads\ToDo.md" backupFilePath="" originalFileLastModifTimestamp="-1667485751" originalFileLastModifTimestampHigh="31158891" tabColourId="-1" RTL="no" tabPinned="no" mapFirstVisibleDisplayLine="-1" mapFirstVisibleDocLine="-1" mapLastVisibleDocLine="-1" mapNbLine="-1" mapHigherPos="-1" mapWidth="-1" mapHeight="-1" mapKByteInDoc="512" mapWrapIndentMode="-1" mapIsWrap="no" />
            <File firstVisibleLine="0" xOffset="0" scrollWidth="220901" startPos="174" endPos="0" selMode="0" offset="0" wrapCount="1" lang="None (Normal Text)" encoding="-1" userReadOnly="no" filename="C:\Users\doria\Downloads\gdrive\RR\2025\20250308__Fisherman&apos;s_Sliding_Challenge_Winteredition\Draft_Fish" backupFilePath="" originalFileLastModifTimestamp="1565319309" originalFileLastModifTimestampHigh="31156491" tabColourId="-1" RTL="no" tabPinned="no" mapFirstVisibleDisplayLine="-1" mapFirstVisibleDocLine="-1" mapLastVisibleDocLine="-1" mapNbLine="-1" mapHigherPos="-1" mapWidth="-1" mapHeight="-1" mapKByteInDoc="512" mapWrapIndentMode="-1" mapIsWrap="no" />
            <File firstVisibleLine="177" xOffset="0" scrollWidth="220901" startPos="8672" endPos="8672" selMode="0" offset="0" wrapCount="1" lang="None (Normal Text)" encoding="-1" userReadOnly="no" filename="C:\Users\doria\Downloads\gdrive\RR\2025\20250419__GP_Osterhas\Draft_GP" backupFilePath="" originalFileLastModifTimestamp="1214959237" originalFileLastModifTimestampHigh="31158452" tabColourId="-1" RTL="no" tabPinned="no" mapFirstVisibleDisplayLine="-1" mapFirstVisibleDocLine="-1" mapLastVisibleDocLine="-1" mapNbLine="-1" mapHigherPos="-1" mapWidth="-1" mapHeight="-1" mapKByteInDoc="512" mapWrapIndentMode="-1" mapIsWrap="no" />
            <File firstVisibleLine="16" xOffset="0" scrollWidth="3347" startPos="1484" endPos="1554" selMode="0" offset="0" wrapCount="1" lang="Batch" encoding="-1" userReadOnly="no" filename="C:\Users\doria\Downloads\GitHub\dorian.gravier.github.io\files\Batch\FFmpeg\Make_it_ALL_v17___FFMPEG.bat" backupFilePath="" originalFileLastModifTimestamp="1438574614" originalFileLastModifTimestampHigh="31159488" tabColourId="-1" RTL="no" tabPinned="no" mapFirstVisibleDisplayLine="-1" mapFirstVisibleDocLine="-1" mapLastVisibleDocLine="-1" mapNbLine="-1" mapHigherPos="-1" mapWidth="-1" mapHeight="-1" mapKByteInDoc="512" mapWrapIndentMode="-1" mapIsWrap="no" />
            <File firstVisibleLine="446" xOffset="0" scrollWidth="3347" startPos="11049" endPos="11049" selMode="0" offset="0" wrapCount="1" lang="Md Drakula" encoding="-1" userReadOnly="no" filename="C:\Users\doria\Downloads\GitHub\dorian.gravier.github.io\_pages\code\bash.md" backupFilePath="" originalFileLastModifTimestamp="1562360358" originalFileLastModifTimestampHigh="31159495" tabColourId="-1" RTL="no" tabPinned="no" mapFirstVisibleDisplayLine="-1" mapFirstVisibleDocLine="-1" mapLastVisibleDocLine="-1" mapNbLine="-1" mapHigherPos="-1" mapWidth="-1" mapHeight="-1" mapKByteInDoc="512" mapWrapIndentMode="-1" mapIsWrap="no" />
            <File firstVisibleLine="0" xOffset="0" scrollWidth="3347" startPos="45" endPos="45" selMode="0" offset="0" wrapCount="1" lang="None (Normal Text)" encoding="-1" userReadOnly="no" filename="new 1" backupFilePath="C:\Users\doria\scoop\apps\notepadplusplus\8.7.5\backup\new 1@2025-02-01_165245" originalFileLastModifTimestamp="0" originalFileLastModifTimestampHigh="0" tabColourId="-1" RTL="no" tabPinned="no" mapFirstVisibleDisplayLine="-1" mapFirstVisibleDocLine="-1" mapLastVisibleDocLine="-1" mapNbLine="-1" mapHigherPos="-1" mapWidth="-1" mapHeight="-1" mapKByteInDoc="512" mapWrapIndentMode="-1" mapIsWrap="no" />
            <File firstVisibleLine="0" xOffset="0" scrollWidth="3347" startPos="69" endPos="69" selMode="0" offset="0" wrapCount="1" lang="None (Normal Text)" encoding="-1" userReadOnly="no" filename="new 2" backupFilePath="C:\Users\doria\scoop\apps\notepadplusplus\8.7.5\backup\new 2@2025-02-01_165323" originalFileLastModifTimestamp="0" originalFileLastModifTimestampHigh="0" tabColourId="-1" RTL="no" tabPinned="no" mapFirstVisibleDisplayLine="-1" mapFirstVisibleDocLine="-1" mapLastVisibleDocLine="-1" mapNbLine="-1" mapHigherPos="-1" mapWidth="-1" mapHeight="-1" mapKByteInDoc="512" mapWrapIndentMode="-1" mapIsWrap="no" />
            <File firstVisibleLine="41" xOffset="0" scrollWidth="3347" startPos="1883" endPos="1766" selMode="0" offset="0" wrapCount="1" lang="Batch" encoding="-1" userReadOnly="no" filename="C:\Users\doria\Downloads\GitHub\dorian.gravier.github.io\files\Batch\FFmpeg\ZoomPanIn_v01___FFMPEG.bat" backupFilePath="" originalFileLastModifTimestamp="-832559848" originalFileLastModifTimestampHigh="31159495" tabColourId="-1" RTL="no" tabPinned="no" mapFirstVisibleDisplayLine="-1" mapFirstVisibleDocLine="-1" mapLastVisibleDocLine="-1" mapNbLine="-1" mapHigherPos="-1" mapWidth="-1" mapHeight="-1" mapKByteInDoc="512" mapWrapIndentMode="-1" mapIsWrap="no" />
        </mainView>
        <subView activeIndex="0" />
    </Session>
</NotepadPlus>
